cdk_alps_graph_ql/__init__.py
cdk_alps_graph_ql/py.typed
cdk_alps_graph_ql/_jsii/__init__.py
cdk_alps_graph_ql/_jsii/cdk-alps-graph-ql@0.0.9.jsii.tgz
cdk_alps_graph_ql-0.0.9.dist-info/METADATA
cdk_alps_graph_ql-0.0.9.dist-info/WHEEL
cdk_alps_graph_ql-0.0.9.dist-info/top_level.txt
cdk_alps_graph_ql-0.0.9.dist-info/RECORD
